hive/__init__.py
hive/agents/__init__.py
hive/agents/agent.py
hive/agents/dqn.py
hive/agents/legal_moves_rainbow.py
hive/agents/rainbow.py
hive/agents/random.py
hive/agents/qnets/__init__.py
hive/agents/qnets/base.py
hive/agents/qnets/conv.py
hive/agents/qnets/mlp.py
hive/agents/qnets/noisy_linear.py
hive/agents/qnets/qnet_heads.py
hive/agents/qnets/utils.py
hive/agents/qnets/atari/__init__.py
hive/agents/qnets/atari/nature_atari_dqn.py
hive/configs/atari/dqn.yml
hive/configs/atari/rainbow.yml
hive/configs/gym/dqn.yml
hive/configs/gym/rainbow.yml
hive/configs/hanabi/rainbow.yml
hive/configs/marlgrid/dqn.yml
hive/configs/marlgrid/rainbow.yml
hive/configs/minatar/dqn.yml
hive/configs/minatar/rainbow.yml
hive/configs/minatar/rainbow_circular_buffer.yml
hive/configs/minigrid/config.yml
hive/envs/__init__.py
hive/envs/base.py
hive/envs/env_spec.py
hive/envs/gym_env.py
hive/envs/atari/__init__.py
hive/envs/atari/atari.py
hive/envs/marlgrid/__init__.py
hive/envs/marlgrid/marlgrid.py
hive/envs/marlgrid/ma_envs/__init__.py
hive/envs/marlgrid/ma_envs/base.py
hive/envs/marlgrid/ma_envs/checkers.py
hive/envs/marlgrid/ma_envs/pursuit.py
hive/envs/marlgrid/ma_envs/switch.py
hive/envs/minatar/__init__.py
hive/envs/minatar/minatar.py
hive/envs/minigrid/__init__.py
hive/envs/minigrid/minigrid.py
hive/envs/pettingzoo/__init__.py
hive/envs/pettingzoo/pettingzoo.py
hive/envs/wrappers/__init__.py
hive/envs/wrappers/gym_wrappers.py
hive/replays/__init__.py
hive/replays/circular_replay.py
hive/replays/legal_moves_replay.py
hive/replays/prioritized_replay.py
hive/replays/replay_buffer.py
hive/runners/__init__.py
hive/runners/base.py
hive/runners/multi_agent_loop.py
hive/runners/single_agent_loop.py
hive/runners/utils.py
hive/utils/__init__.py
hive/utils/experiment.py
hive/utils/loggers.py
hive/utils/registry.py
hive/utils/schedule.py
hive/utils/torch_utils.py
hive/utils/utils.py
hive/utils/visualization.py
rlhive-1.0.1.dist-info/AUTHORS
rlhive-1.0.1.dist-info/LICENSE
rlhive-1.0.1.dist-info/METADATA
rlhive-1.0.1.dist-info/WHEEL
rlhive-1.0.1.dist-info/entry_points.txt
rlhive-1.0.1.dist-info/top_level.txt
rlhive-1.0.1.dist-info/RECORD
