Metadata-Version: 2.1
Name: rlhive
Version: 1.0.1
Summary: A package to support RL research
Home-page: https://github.com/chandar-lab/RLHive
License: UNKNOWN
Project-URL: Bug Tracker, https://github.com/chandar-lab/RLHive/issues
Platform: UNKNOWN
Classifier: Programming Language :: Python :: 3
Classifier: Programming Language :: Python :: 3.6
Classifier: Programming Language :: Python :: 3.7
Classifier: Programming Language :: Python :: 3.8
Classifier: Programming Language :: Python :: 3.9
Requires-Python: >=3.6
License-File: LICENSE
License-File: AUTHORS
Requires-Dist: gym (~=0.21)
Requires-Dist: numpy (~=1.18)
Requires-Dist: PyYAML (~=5.4)
Requires-Dist: torch (~=1.6)
Requires-Dist: wandb (>=0.10.30)
Requires-Dist: matplotlib (~=3.0)
Requires-Dist: pandas (~=1.0)
Provides-Extra: all
Requires-Dist: gym[accept-rom-license,atari] (~=0.21) ; extra == 'all'
Requires-Dist: opencv-python (~=4.0) ; extra == 'all'
Requires-Dist: gym-minigrid (~=1.0) ; extra == 'all'
Requires-Dist: pettingzoo[atari,classic,sisl] (~=1.11) ; extra == 'all'
Requires-Dist: pytest (~=6.2) ; extra == 'all'
Requires-Dist: pytest-lazy-fixture (~=0.6) ; extra == 'all'
Provides-Extra: atari
Requires-Dist: gym[accept-rom-license,atari] (~=0.21) ; extra == 'atari'
Requires-Dist: opencv-python (~=4.0) ; extra == 'atari'
Provides-Extra: gym_minigrid
Requires-Dist: gym-minigrid (~=1.0) ; extra == 'gym_minigrid'
Provides-Extra: petting_zoo
Requires-Dist: pettingzoo[atari,classic,sisl] (~=1.11) ; extra == 'petting_zoo'
Provides-Extra: test
Requires-Dist: pytest (~=6.2) ; extra == 'test'
Requires-Dist: pytest-lazy-fixture (~=0.6) ; extra == 'test'
